cc/scpi/__init__.py
cc/scpi/generic_instrument.py
cc.scpi-2024.8.31.dist-info/LICENSE
cc.scpi-2024.8.31.dist-info/METADATA
cc.scpi-2024.8.31.dist-info/WHEEL
cc.scpi-2024.8.31.dist-info/top_level.txt
cc.scpi-2024.8.31.dist-info/RECORD
