Metadata-Version: 2.1
Name: cc.scpi
Version: 2024.8.31
Summary: Wrapper of SCPI language for controlling various lab instruments.
Home-page: https://github.com/uncertainty-cc/SCPI-Python
Author: Uncertainty.
Author-email: t_k_233@outlook.email
Classifier: Programming Language :: Python :: 3
Classifier: License :: OSI Approved :: MIT License
Classifier: Operating System :: OS Independent
Requires-Python: >=3.8
License-File: LICENSE
Requires-Dist: cc-serializer
